{
    "id": "7abde8c8236909856fa6f6159acb1413",
    "name": "Top Stories",
    "description": null,
    "auth": null,
    "events": null,
    "variables": [],
    "order": [],
    "folders_order": [],
    "folders": [],
    "requests": [
        {
            "id": "dc49d17237ec5fca6a2be7995b42f0cf",
            "name": "Top Stories",
            "url": "http:\/\/api.nytimes.com\/svc\/topstories\/v2\/{section}.{format}",
            "description": "The Top Stories API returns a list of articles and associated images currently on the specified section.  Support JSON and JSONP.\n",
            "data": [],
            "dataMode": "raw",
            "headerData": null,
            "method": "get",
            "pathVariableData": [],
            "queryParams": [
                {
                    "key": "section",
                    "description": "The section the story appears in.",
                    "value": "",
                    "equals": true,
                    "enabled": true
                },
                {
                    "key": "format",
                    "description": "if this is JSONP or JSON",
                    "value": "",
                    "equals": true,
                    "enabled": true
                },
                {
                    "key": "callback",
                    "description": "The name of the function the API call results will be passed to. Required when using JSONP. This parameter has only one valid value per section. The format is {section_name}TopStoriesCallback.\n",
                    "value": "",
                    "equals": true,
                    "enabled": true
                }
            ],
            "auth": null,
            "events": null,
            "folder": null,
            "protocolProfileBehavior": {
                "disableBodyPruning": true
            },
            "responses": [],
            "currentHelper": null,
            "helperAttributes": null,
            "collectionId": "7abde8c8236909856fa6f6159acb1413",
            "rawModeData": ""
        }
    ]
}